rpdll/__init__.py
rpdll/__init__.pyi
rpdll/__main__.py
rpdll/cli.py
rpdll/py.typed
rpdll/modules/__init__.py
rpdll/modules/ansi.py
rpdll/modules/log.py
rpdll/modules/metadata.py
rpdll/modules/pe.py
rpdll/modules/rusty.py
rpdll/modules/template.py
rpdll/modules/parsing/__init__.py
rpdll/modules/parsing/parents.py
rpdll/modules/parsing/parsers/__init__.py
rpdll/modules/parsing/parsers/main.py
rpdll/parsers/__init__.py
rpdll/parsers/main.py
rpdll/parsers/types.py
rpdll/templates/build.jinja
rpdll/templates/lib.jinja
rpdll-0.0.1.dist-info/licenses/LICENSE
rpdll-0.0.1.dist-info/METADATA
rpdll-0.0.1.dist-info/WHEEL
rpdll-0.0.1.dist-info/entry_points.txt
rpdll-0.0.1.dist-info/top_level.txt
rpdll-0.0.1.dist-info/RECORD
