Metadata-Version: 2.4
Name: rpdll
Version: 0.0.1
Summary: Easy-to-use proxy DLL generator.
Author-email: Stefano Cuizza <stefano.cuizza@protonmail.com>
Maintainer-email: Stefano Cuizza <stefano.cuizza@protonmail.com>
License:                     GNU GENERAL PUBLIC LICENSE
Project-URL: Github, https://github.com/x55xaa/proxy-dll
Keywords: proxy dll,rust
Classifier: Development Status :: 4 - Beta
Classifier: Intended Audience :: End Users/Desktop
Classifier: License :: OSI Approved :: GNU General Public License v3 (GPLv3)
Classifier: Operating System :: Microsoft :: Windows
Requires-Python: >=3.12
License-File: LICENSE
Requires-Dist: colorama
Requires-Dist: jinja2
Requires-Dist: pefile
Requires-Dist: toml
Provides-Extra: docs
Requires-Dist: myst_parser; extra == "docs"
Requires-Dist: sphinx; extra == "docs"
Requires-Dist: sphinx-argparse; extra == "docs"
Requires-Dist: sphinx_autodoc_typehints; extra == "docs"
Requires-Dist: sphinx_rtd_theme; extra == "docs"
Provides-Extra: testing
Requires-Dist: pylint; extra == "testing"
Requires-Dist: pytest; extra == "testing"
Requires-Dist: pytest-cov; extra == "testing"
Requires-Dist: ruff; extra == "testing"
Requires-Dist: tox; extra == "testing"
Dynamic: license-file
